{
    "pools": [
        {
            "rolls": 1,
            "entries": [
                {
                    "type": "empty",
                    "weight": 1
                },
                {
                    "type": "item",
                    "name": "minecraft:paper",
                    "functions": [
                        {
                            "function": "set_nbt",
                            "tag": "{rnd:yellow,color:1}"
                        }
                    ],
                    "weight": 1
                },
                {
                    "type": "item",
                    "name": "minecraft:paper",
                    "functions": [
                        {
                            "function": "set_nbt",
                            "tag": "{rnd:blue,color:1}"
                        }
                    ],
                    "weight": 1
                },
                {
                    "type": "item",
                    "name": "minecraft:paper",
                    "functions": [
                        {
                            "function": "set_nbt",
                            "tag": "{rnd:lime,color:1}"
                        }
                    ],
                    "weight": 1
                },
                {
                    "type": "item",
                    "name": "minecraft:paper",
                    "functions": [
                        {
                            "function": "set_nbt",
                            "tag": "{rnd:green,color:1}"
                        }
                    ],
                    "weight": 1
                },
                {
                    "type": "item",
                    "name": "minecraft:paper",
                    "functions": [
                        {
                            "function": "set_nbt",
                            "tag": "{rnd:red,color:1}"
                        }
                    ],
                    "weight": 1
                },
                {
                    "type": "item",
                    "name": "minecraft:paper",
                    "functions": [
                        {
                            "function": "set_nbt",
                            "tag": "{rnd:light_blue,color:1}"
                        }
                    ],
                    "weight": 1
                },
                {
                    "type": "item",
                    "name": "minecraft:paper",
                    "functions": [
                        {
                            "function": "set_nbt",
                            "tag": "{rnd:magenta,color:1}"
                        }
                    ],
                    "weight": 1
                }
            ]
        }
    ]
}